setup.cfg
setup.py
TOPSIS_Divyanshu_101803542/TOPSIS.py
TOPSIS_Divyanshu_101803542/__init__.py
TOPSIS_Divyanshu_101803542.egg-info/PKG-INFO
TOPSIS_Divyanshu_101803542.egg-info/SOURCES.txt
TOPSIS_Divyanshu_101803542.egg-info/dependency_links.txt
TOPSIS_Divyanshu_101803542.egg-info/requires.txt
TOPSIS_Divyanshu_101803542.egg-info/top_level.txt