Metadata-Version: 1.1
Name: TOPSIS-Divyanshu-101803542
Version: 0.3
Summary: Python package implementing TOPSIS 
Home-page: https://github.com/dishu5312/Topsis.git
Author: Divyanshu Srivastava
Author-email: dsrivastava_be18@thapar.edu
License: MIT
Download-URL: https://github.com/dishu5312/Topsis/archive/v_01.tar.gz
Keywords: TOPSIS,IMPLEMENTATION,PYTHON
Platform: UNKNOWN
Classifier: License :: OSI Approved :: MIT License
Classifier: Programming Language :: Python :: 3
Classifier: Programming Language :: Python :: 3.7
